<?xml version="1.0" encoding="UTF-8"?>
<features name="${project.artifactId}-${project.version}"
	xmlns="http://karaf.apache.org/xmlns/features/v1.0.0" xmlns:xsi="http://www.w3.org/2001/XMLSchema-instance"
	xsi:schemaLocation="http://karaf.apache.org/xmlns/features/v1.0.0 http://karaf.apache.org/xmlns/features/v1.0.0">


	<feature name="panda-development-all" version="${project.version}">


		<bundle>wrap:mvn:org.apache.commons/commons-lang3/3.4</bundle>

		<bundle>mvn:org.enjekt.panda/commons/${project.version}</bundle>
		<bundle>mvn:org.enjekt.panda/developmentkit/${project.version}</bundle>
		<bundle>mvn:org.enjekt.panda/whitevault/${project.version}</bundle>
		<bundle>mvn:org.enjekt.panda/blackvault/${project.version}</bundle>
		<bundle>mvn:org.enjekt.panda/whitevaultserver/${project.version}</bundle>

	</feature>

</features>